gixy/__init__.py
gixy/cli/__init__.py
gixy/cli/argparser.py
gixy/cli/main.py
gixy/core/__init__.py
gixy/core/builtin_variables.py
gixy/core/config.py
gixy/core/context.py
gixy/core/exceptions.py
gixy/core/issue.py
gixy/core/manager.py
gixy/core/plugins_manager.py
gixy/core/regexp.py
gixy/core/severity.py
gixy/core/utils.py
gixy/core/variable.py
gixy/core/sre_parse/__init__.py
gixy/core/sre_parse/sre_constants.py
gixy/core/sre_parse/sre_parse.py
gixy/directives/__init__.py
gixy/directives/block.py
gixy/directives/directive.py
gixy/formatters/__init__.py
gixy/formatters/_jinja.py
gixy/formatters/base.py
gixy/formatters/console.py
gixy/formatters/json.py
gixy/formatters/text.py
gixy/formatters/templates/console.j2
gixy/formatters/templates/text.j2
gixy/parser/__init__.py
gixy/parser/nginx_parser.py
gixy/parser/raw_parser.py
gixy/plugins/__init__.py
gixy/plugins/add_header_multiline.py
gixy/plugins/add_header_redefinition.py
gixy/plugins/alias_traversal.py
gixy/plugins/host_spoofing.py
gixy/plugins/http_splitting.py
gixy/plugins/origins.py
gixy/plugins/plugin.py
gixy/plugins/ssrf.py
gixy/plugins/valid_referers.py
gixy/utils/__init__.py
gixy/utils/text.py
gixy-0.1.21.dist-info/AUTHORS
gixy-0.1.21.dist-info/LICENSE
gixy-0.1.21.dist-info/METADATA
gixy-0.1.21.dist-info/WHEEL
gixy-0.1.21.dist-info/entry_points.txt
gixy-0.1.21.dist-info/top_level.txt
gixy-0.1.21.dist-info/RECORD
