Metadata-Version: 2.1
Name: gixy
Version: 0.1.21
Summary: Nginx configuration [sec]analyzer
Home-page: https://github.com/yandex/gixy
Author: Yandex IS Team
Author-email: buglloc@yandex.ru
Keywords: nginx security lint static-analysis
Classifier: Development Status :: 3 - Alpha
Classifier: Environment :: Console
Classifier: Intended Audience :: System Administrators
Classifier: Intended Audience :: Developers
Classifier: Topic :: Security
Classifier: Topic :: Software Development :: Quality Assurance
Classifier: Topic :: Software Development :: Testing
License-File: LICENSE
License-File: AUTHORS
Requires-Dist: pyparsing <3,>=1.5.5
Requires-Dist: cached-property >=1.2.0
Requires-Dist: six >=1.1.0
Requires-Dist: Jinja2 >=2.8
Requires-Dist: ConfigArgParse >=0.11.0
Requires-Dist: argparse >=1.4.0 ; python_version < "3.2"
